libname/__init__.py
libname/demo.py
textDetect-0.0.1.dist-info/METADATA
textDetect-0.0.1.dist-info/WHEEL
textDetect-0.0.1.dist-info/top_level.txt
textDetect-0.0.1.dist-info/RECORD
